nllegalcit/__init__.py
nllegalcit/citations.py
nllegalcit/errors.py
nllegalcit/parser.py
nllegalcit/utils.py
nllegalcit/visitors.py
nllegalcit/grammars/caselaw.lark
nllegalcit/grammars/citations.lark
nllegalcit/grammars/parlementair.lark
nllegalcit-0.0.4.dist-info/LICENSE
nllegalcit-0.0.4.dist-info/METADATA
nllegalcit-0.0.4.dist-info/WHEEL
nllegalcit-0.0.4.dist-info/top_level.txt
nllegalcit-0.0.4.dist-info/RECORD
