Metadata-Version: 2.1
Name: nllegalcit
Version: 0.0.4
Summary: Python library to find citations to Dutch legal documents in natural language text
Author-email: Martijn Staal <nllegalcit@martijn-staal.nl>
Project-URL: Homepage, https://github.com/mastaal/nllegalcit
Project-URL: Issues, https://github.com/mastaal/nllegalcit/issues
Project-URL: Documentation, https://nllegalcit.martijn-staal.nl/latest
Classifier: Development Status :: 3 - Alpha
Classifier: Programming Language :: Python :: 3 :: Only
Classifier: License :: OSI Approved :: European Union Public Licence 1.2 (EUPL 1.2)
Classifier: Intended Audience :: Legal Industry
Classifier: Intended Audience :: Science/Research
Requires-Python: >=3.10
License-File: LICENSE
Requires-Dist: lark >=1.1.8
Requires-Dist: requests >=2.31.0
Requires-Dist: pypdf >=3.17.2
Requires-Dist: cryptography >=41.0.7
